Florence-0.1.4.data/purelib/Florence/__init__.py
Florence-0.1.4.data/purelib/Florence/Base/Base.py
Florence-0.1.4.data/purelib/Florence/Base/FlorenceExceptions.py
Florence-0.1.4.data/purelib/Florence/Base/__init__.py
Florence-0.1.4.data/purelib/Florence/BoundaryCondition/BoundaryCondition.py
Florence-0.1.4.data/purelib/Florence/BoundaryCondition/__init__.py
Florence-0.1.4.data/purelib/Florence/BoundaryElements/Assembly.py
Florence-0.1.4.data/purelib/Florence/BoundaryElements/GetBases.py
Florence-0.1.4.data/purelib/Florence/BoundaryElements/PostProcessBEM2D.py
Florence-0.1.4.data/purelib/Florence/BoundaryElements/PreProcessBEM2D.py
Florence-0.1.4.data/purelib/Florence/BoundaryElements/Sort_BEM.py
Florence-0.1.4.data/purelib/Florence/BoundaryElements/WritePlotBEM2D.py
Florence-0.1.4.data/purelib/Florence/BoundaryElements/__init__.py
Florence-0.1.4.data/purelib/Florence/FiniteElements/__init__.py
Florence-0.1.4.data/purelib/Florence/FiniteElements/Assembly/Assembly.py
Florence-0.1.4.data/purelib/Florence/FiniteElements/Assembly/MPIParallelExplicitAssembler.py
Florence-0.1.4.data/purelib/Florence/FiniteElements/Assembly/RHSAssemblyNative.so
Florence-0.1.4.data/purelib/Florence/FiniteElements/Assembly/SparseAssemblyNative.so
Florence-0.1.4.data/purelib/Florence/FiniteElements/Assembly/_LowLevelAssemblyDF__AnisotropicMooneyRivlin_1_.so
Florence-0.1.4.data/purelib/Florence/FiniteElements/Assembly/_LowLevelAssemblyDF__LinearElastic_.so
Florence-0.1.4.data/purelib/Florence/FiniteElements/Assembly/_LowLevelAssemblyDF__MooneyRivlin_.so
Florence-0.1.4.data/purelib/Florence/FiniteElements/Assembly/_LowLevelAssemblyDF__NearlyIncompressibleMooneyRivlin_.so
Florence-0.1.4.data/purelib/Florence/FiniteElements/Assembly/_LowLevelAssemblyDF__NeoHookean_.so
Florence-0.1.4.data/purelib/Florence/FiniteElements/Assembly/_LowLevelAssemblyDPF__IsotropicElectroMechanics_0_.so
Florence-0.1.4.dist-info/METADATA
Florence-0.1.4.dist-info/RECORD
Florence-0.1.4.dist-info/WHEEL
Florence-0.1.4.dist-info/top_level.txt
