Metadata-Version: 2.1
Name: Florence
Version: 0.1.4
Summary: A Python based computational framework for integrated computer aided design,
Home-page: https://github.com/romeric/florence
Author: Roman Poya
Author-email: roman_poya@yahoo.com
License: MIT
Platform: Linux
Platform: macOS
Platform: Unix
Platform: Windows
Requires-Python: >=2.7,!=3.0.*,!=3.1.*,!=3.2.*,!=3.3.*,!=3.4.*
Requires-Dist: cython (>=0.23)
Requires-Dist: numpy (>=1.9)
Requires-Dist: scipy (>=0.14)
Requires-Dist: scikit-umfpack (>=0.2)
